design.sv
/*
Name: MD. Nazimuddowla
Desgin: 8-bit up-down asynchonus counter
date: 12th December, 2107
*/


//	Module	//

module COUNT (
  clk,
  up,
  down,
  rst,
  en,
  c_out
);
  
  
//	Outputs	//
  output [7:0] c_out;
  
//	Input	//
  input clk;
  input up;
  input down;
  input rst;
  input en;
  
//	Internal	//
  reg [7:0] store;
  
  
// Operation	//
  always @(posedge clk) begin
    if (rst) begin
      store = 8'b0;
    end
    else if (en) begin
      if (up) begin
        if (store == 11111111) begin
          store = 8'b0;
        end
        else begin
          store = store + 1;
        end
        end
      else if (down) begin
        store = store - 1;
      end
    end
  end
  
  assign c_out = store;
  
  
endmodule

testbench.sv
/*
Name: MD. Nazimuddowla
Desgin: 8-bit up-down asynchonus counter test bech
date: 12th December, 2107
*/


//	Module	//
module count;
  reg clk;
  reg up;
  reg down;
  reg rst;
  reg en;
  wire c_out;
  
  
// DUT Connections	//
  COUNT count (
    .clk(clk),
    .up(up),
    .down(down),
    .en(en),
    .rst(rst),
    .c_out(c_out)
  );
  
  
//	Clock Generation	//
  initial forever #10 clk = ~clk;
  initial forever #160 up = ~up;
  initial forever #40 down = ~down;
  initial forever #1000 en = ~en;
  
  initial begin
    clk = 0;
    up = 0;
    down = 0;
    en = 1;
    rst = 1;
    
    #30
    rst = 0;
    
  end
  
//	Simulation Time		//
  initial begin
    #5000
    $finish;
  end
  
  
//	Waveform	//
  initial begin
    $dumpfile ("dump.vcd");
    $dumpvars;
  end
  
endmodule

dump.vcd
$date
    Oct 22, 2018  05:10:09
$end
$version
    TOOL:	ncsim	15.20-s038
$end
$timescale
    1 ns
$end

$scope module count $end
$var reg       1 !    clk  $end
$var reg       1 "    up  $end
$var reg       1 #    down  $end
$var reg       1 $    rst  $end
$var reg       1 %    en  $end
$var wire      1 &    c_out  $end

$scope module count $end
$var wire      1 '    c_out [7] $end
$var wire      1 (    c_out [6] $end
$var wire      1 )    c_out [5] $end
$var wire      1 *    c_out [4] $end
$var wire      1 +    c_out [3] $end
$var wire      1 ,    c_out [2] $end
$var wire      1 -    c_out [1] $end
$var wire      1 &    c_out [0] $end
$var wire      1 .    clk  $end
$var wire      1 /    up  $end
$var wire      1 0    down  $end
$var wire      1 1    rst  $end
$var wire      1 2    en  $end
$var reg       8 3    store [7:0] $end
$upscope $end

$upscope $end

$enddefinitions $end
$dumpvars
0!
0"
0#
1$
1%
x&
x'
x(
x)
x*
x+
x,
x-
0.
0/
00
11
12
bx 3
$end
#10
1!
1.
b0 3
0'
0(
0)
0*
0+
0,
0-
0&
#20
0!
0.
#30
0$
1!
1.
01
#40
1#
0!
0.
10
#50
1!
1.
b11111111 3
1'
1(
1)
1*
1+
1,
1-
1&
#60
0!
0.
#70
1!
1.
b11111110 3
0&
#80
0#
0!
0.
00
#90
1!
1.
#100
0!
0.
#110
1!
1.
#120
1#
0!
0.
10
#130
1!
1.
b11111101 3
0-
1&
#140
0!
0.
#150
1!
1.
b11111100 3
0&
#160
1"
0#
0!
0.
00
1/
#170
1!
1.
b11111101 3
1&
#180
0!
0.
#190
1!
1.
b11111110 3
1-
0&
#200
1#
0!
0.
10
#210
1!
1.
b11111111 3
1&
#220
0!
0.
#230
1!
1.
b0 3
0'
0(
0)
0*
0+
0,
0-
0&
#240
0#
0!
0.
00
#250
1!
1.
b1 3
1&
#260
0!
0.
#270
1!
1.
b10 3
1-
0&
#280
1#
0!
0.
10
#290
1!
1.
b11 3
1&
#300
0!
0.
#310
1!
1.
b100 3
1,
0-
0&
#320
0"
0#
0!
0.
00
0/
#330
1!
1.
#340
0!
0.
#350
1!
1.
#360
1#
0!
0.
10
#370
1!
1.
b11 3
0,
1-
1&
#380
0!
0.
#390
1!
1.
b10 3
0&
#400
0#
0!
0.
00
#410
1!
1.
#420
0!
0.
#430
1!
1.
#440
1#
0!
0.
10
#450
1!
1.
b1 3
0-
1&
#460
0!
0.
#470
1!
1.
b0 3
0&
#480
1"
0#
0!
0.
00
1/
#490
1!
1.
b1 3
1&
#500
0!
0.
#510
1!
1.
b10 3
1-
0&
#520
1#
0!
0.
10
#530
1!
1.
b11 3
1&
#540
0!
0.
#550
1!
1.
b100 3
1,
0-
0&
#560
0#
0!
0.
00
#570
1!
1.
b101 3
1&
#580
0!
0.
#590
1!
1.
b110 3
1-
0&
#600
1#
0!
0.
10
#610
1!
1.
b111 3
1&
#620
0!
0.
#630
1!
1.
b1000 3
1+
0,
0-
0&
#640
0"
0#
0!
0.
00
0/
#650
1!
1.
#660
0!
0.
#670
1!
1.
#680
1#
0!
0.
10
#690
1!
1.
b111 3
0+
1,
1-
1&
#700
0!
0.
#710
1!
1.
b110 3
0&
#720
0#
0!
0.
00
#730
1!
1.
#740
0!
0.
#750
1!
1.
#760
1#
0!
0.
10
#770
1!
1.
b101 3
0-
1&
#780
0!
0.
#790
1!
1.
b100 3
0&
#800
1"
0#
0!
0.
00
1/
#810
1!
1.
b101 3
1&
#820
0!
0.
#830
1!
1.
b110 3
1-
0&
#840
1#
0!
0.
10
#850
1!
1.
b111 3
1&
#860
0!
0.
#870
1!
1.
b1000 3
1+
0,
0-
0&
#880
0#
0!
0.
00
#890
1!
1.
b1001 3
1&
#900
0!
0.
#910
1!
1.
b1010 3
1-
0&
#920
1#
0!
0.
10
#930
1!
1.
b1011 3
1&
#940
0!
0.
#950
1!
1.
b1100 3
1,
0-
0&
#960
0"
0#
0!
0.
00
0/
#970
1!
1.
#980
0!
0.
#990
1!
1.
#1000
0%
1#
0!
0.
10
02
#1010
1!
1.
#1020
0!
0.
#1030
1!
1.
#1040
0#
0!
0.
00
#1050
1!
1.
#1060
0!
0.
#1070
1!
1.
#1080
1#
0!
0.
10
#1090
1!
1.
#1100
0!
0.
#1110
1!
1.
#1120
1"
0#
0!
0.
00
1/
#1130
1!
1.
#1140
0!
0.
#1150
1!
1.
#1160
1#
0!
0.
10
#1170
1!
1.
#1180
0!
0.
#1190
1!
1.
#1200
0#
0!
0.
00
#1210
1!
1.
#1220
0!
0.
#1230
1!
1.
#1240
1#
0!
0.
10
#1250
1!
1.
#1260
0!
0.
#1270
1!
1.
#1280
0"
0#
0!
0.
00
0/
#1290
1!
1.
#1300
0!
0.
#1310
1!
1.
#1320
1#
0!
0.
10
#1330
1!
1.
#1340
0!
0.
#1350
1!
1.
#1360
0#
0!
0.
00
#1370
1!
1.
#1380
0!
0.
#1390
1!
1.
#1400
1#
0!
0.
10
#1410
1!
1.
#1420
0!
0.
#1430
1!
1.
#1440
1"
0#
0!
0.
00
1/
#1450
1!
1.
#1460
0!
0.
#1470
1!
1.
#1480
1#
0!
0.
10
#1490
1!
1.
#1500
0!
0.
#1510
1!
1.
#1520
0#
0!
0.
00
#1530
1!
1.
#1540
0!
0.
#1550
1!
1.
#1560
1#
0!
0.
10
#1570
1!
1.
#1580
0!
0.
#1590
1!
1.
#1600
0"
0#
0!
0.
00
0/
#1610
1!
1.
#1620
0!
0.
#1630
1!
1.
#1640
1#
0!
0.
10
#1650
1!
1.
#1660
0!
0.
#1670
1!
1.
#1680
0#
0!
0.
00
#1690
1!
1.
#1700
0!
0.
#1710
1!
1.
#1720
1#
0!
0.
10
#1730
1!
1.
#1740
0!
0.
#1750
1!
1.
#1760
1"
0#
0!
0.
00
1/
#1770
1!
1.
#1780
0!
0.
#1790
1!
1.
#1800
1#
0!
0.
10
#1810
1!
1.
#1820
0!
0.
#1830
1!
1.
#1840
0#
0!
0.
00
#1850
1!
1.
#1860
0!
0.
#1870
1!
1.
#1880
1#
0!
0.
10
#1890
1!
1.
#1900
0!
0.
#1910
1!
1.
#1920
0"
0#
0!
0.
00
0/
#1930
1!
1.
#1940
0!
0.
#1950
1!
1.
#1960
1#
0!
0.
10
#1970
1!
1.
#1980
0!
0.
#1990
1!
1.
#2000
1%
0#
0!
0.
00
12
#2010
1!
1.
#2020
0!
0.
#2030
1!
1.
#2040
1#
0!
0.
10
#2050
1!
1.
b1011 3
0,
1-
1&
#2060
0!
0.
#2070
1!
1.
b1010 3
0&
#2080
1"
0#
0!
0.
00
1/
#2090
1!
1.
b1011 3
1&
#2100
0!
0.
#2110
1!
1.
b1100 3
1,
0-
0&
#2120
1#
0!
0.
10
#2130
1!
1.
b1101 3
1&
#2140
0!
0.
#2150
1!
1.
b1110 3
1-
0&
#2160
0#
0!
0.
00
#2170
1!
1.
b1111 3
1&
#2180
0!
0.
#2190
1!
1.
b10000 3
1*
0+
0,
0-
0&
#2200
1#
0!
0.
10
#2210
1!
1.
b10001 3
1&
#2220
0!
0.
#2230
1!
1.
b10010 3
1-
0&
#2240
0"
0#
0!
0.
00
0/
#2250
1!
1.
#2260
0!
0.
#2270
1!
1.
#2280
1#
0!
0.
10
#2290
1!
1.
b10001 3
0-
1&
#2300
0!
0.
#2310
1!
1.
b10000 3
0&
#2320
0#
0!
0.
00
#2330
1!
1.
#2340
0!
0.
#2350
1!
1.
#2360
1#
0!
0.
10
#2370
1!
1.
b1111 3
0*
1+
1,
1-
1&
#2380
0!
0.
#2390
1!
1.
b1110 3
0&
#2400
1"
0#
0!
0.
00
1/
#2410
1!
1.
b1111 3
1&
#2420
0!
0.
#2430
1!
1.
b10000 3
1*
0+
0,
0-
0&
#2440
1#
0!
0.
10
#2450
1!
1.
b10001 3
1&
#2460
0!
0.
#2470
1!
1.
b10010 3
1-
0&
#2480
0#
0!
0.
00
#2490
1!
1.
b10011 3
1&
#2500
0!
0.
#2510
1!
1.
b10100 3
1,
0-
0&
#2520
1#
0!
0.
10
#2530
1!
1.
b10101 3
1&
#2540
0!
0.
#2550
1!
1.
b10110 3
1-
0&
#2560
0"
0#
0!
0.
00
0/
#2570
1!
1.
#2580
0!
0.
#2590
1!
1.
#2600
1#
0!
0.
10
#2610
1!
1.
b10101 3
0-
1&
#2620
0!
0.
#2630
1!
1.
b10100 3
0&
#2640
0#
0!
0.
00
#2650
1!
1.
#2660
0!
0.
#2670
1!
1.
#2680
1#
0!
0.
10
#2690
1!
1.
b10011 3
0,
1-
1&
#2700
0!
0.
#2710
1!
1.
b10010 3
0&
#2720
1"
0#
0!
0.
00
1/
#2730
1!
1.
b10011 3
1&
#2740
0!
0.
#2750
1!
1.
b10100 3
1,
0-
0&
#2760
1#
0!
0.
10
#2770
1!
1.
b10101 3
1&
#2780
0!
0.
#2790
1!
1.
b10110 3
1-
0&
#2800
0#
0!
0.
00
#2810
1!
1.
b10111 3
1&
#2820
0!
0.
#2830
1!
1.
b11000 3
1+
0,
0-
0&
#2840
1#
0!
0.
10
#2850
1!
1.
b11001 3
1&
#2860
0!
0.
#2870
1!
1.
b11010 3
1-
0&
#2880
0"
0#
0!
0.
00
0/
#2890
1!
1.
#2900
0!
0.
#2910
1!
1.
#2920
1#
0!
0.
10
#2930
1!
1.
b11001 3
0-
1&
#2940
0!
0.
#2950
1!
1.
b11000 3
0&
#2960
0#
0!
0.
00
#2970
1!
1.
#2980
0!
0.
#2990
1!
1.
#3000
0%
1#
0!
0.
10
02
#3010
1!
1.
#3020
0!
0.
#3030
1!
1.
#3040
1"
0#
0!
0.
00
1/
#3050
1!
1.
#3060
0!
0.
#3070
1!
1.
#3080
1#
0!
0.
10
#3090
1!
1.
#3100
0!
0.
#3110
1!
1.
#3120
0#
0!
0.
00
#3130
1!
1.
#3140
0!
0.
#3150
1!
1.
#3160
1#
0!
0.
10
#3170
1!
1.
#3180
0!
0.
#3190
1!
1.
#3200
0"
0#
0!
0.
00
0/
#3210
1!
1.
#3220
0!
0.
#3230
1!
1.
#3240
1#
0!
0.
10
#3250
1!
1.
#3260
0!
0.
#3270
1!
1.
#3280
0#
0!
0.
00
#3290
1!
1.
#3300
0!
0.
#3310
1!
1.
#3320
1#
0!
0.
10
#3330
1!
1.
#3340
0!
0.
#3350
1!
1.
#3360
1"
0#
0!
0.
00
1/
#3370
1!
1.
#3380
0!
0.
#3390
1!
1.
#3400
1#
0!
0.
10
#3410
1!
1.
#3420
0!
0.
#3430
1!
1.
#3440
0#
0!
0.
00
#3450
1!
1.
#3460
0!
0.
#3470
1!
1.
#3480
1#
0!
0.
10
#3490
1!
1.
#3500
0!
0.
#3510
1!
1.
#3520
0"
0#
0!
0.
00
0/
#3530
1!
1.
#3540
0!
0.
#3550
1!
1.
#3560
1#
0!
0.
10
#3570
1!
1.
#3580
0!
0.
#3590
1!
1.
#3600
0#
0!
0.
00
#3610
1!
1.
#3620
0!
0.
#3630
1!
1.
#3640
1#
0!
0.
10
#3650
1!
1.
#3660
0!
0.
#3670
1!
1.
#3680
1"
0#
0!
0.
00
1/
#3690
1!
1.
#3700
0!
0.
#3710
1!
1.
#3720
1#
0!
0.
10
#3730
1!
1.
#3740
0!
0.
#3750
1!
1.
#3760
0#
0!
0.
00
#3770
1!
1.
#3780
0!
0.
#3790
1!
1.
#3800
1#
0!
0.
10
#3810
1!
1.
#3820
0!
0.
#3830
1!
1.
#3840
0"
0#
0!
0.
00
0/
#3850
1!
1.
#3860
0!
0.
#3870
1!
1.
#3880
1#
0!
0.
10
#3890
1!
1.
#3900
0!
0.
#3910
1!
1.
#3920
0#
0!
0.
00
#3930
1!
1.
#3940
0!
0.
#3950
1!
1.
#3960
1#
0!
0.
10
#3970
1!
1.
#3980
0!
0.
#3990
1!
1.
#4000
1%
1"
0#
0!
0.
00
1/
12
#4010
1!
1.
b11001 3
1&
#4020
0!
0.
#4030
1!
1.
b11010 3
1-
0&
#4040
1#
0!
0.
10
#4050
1!
1.
b11011 3
1&
#4060
0!
0.
#4070
1!
1.
b11100 3
1,
0-
0&
#4080
0#
0!
0.
00
#4090
1!
1.
b11101 3
1&
#4100
0!
0.
#4110
1!
1.
b11110 3
1-
0&
#4120
1#
0!
0.
10
#4130
1!
1.
b11111 3
1&
#4140
0!
0.
#4150
1!
1.
b100000 3
1)
0*
0+
0,
0-
0&
#4160
0"
0#
0!
0.
00
0/
#4170
1!
1.
#4180
0!
0.
#4190
1!
1.
#4200
1#
0!
0.
10
#4210
1!
1.
b11111 3
0)
1*
1+
1,
1-
1&
#4220
0!
0.
#4230
1!
1.
b11110 3
0&
#4240
0#
0!
0.
00
#4250
1!
1.
#4260
0!
0.
#4270
1!
1.
#4280
1#
0!
0.
10
#4290
1!
1.
b11101 3
0-
1&
#4300
0!
0.
#4310
1!
1.
b11100 3
0&
#4320
1"
0#
0!
0.
00
1/
#4330
1!
1.
b11101 3
1&
#4340
0!
0.
#4350
1!
1.
b11110 3
1-
0&
#4360
1#
0!
0.
10
#4370
1!
1.
b11111 3
1&
#4380
0!
0.
#4390
1!
1.
b100000 3
1)
0*
0+
0,
0-
0&
#4400
0#
0!
0.
00
#4410
1!
1.
b100001 3
1&
#4420
0!
0.
#4430
1!
1.
b100010 3
1-
0&
#4440
1#
0!
0.
10
#4450
1!
1.
b100011 3
1&
#4460
0!
0.
#4470
1!
1.
b100100 3
1,
0-
0&
#4480
0"
0#
0!
0.
00
0/
#4490
1!
1.
#4500
0!
0.
#4510
1!
1.
#4520
1#
0!
0.
10
#4530
1!
1.
b100011 3
0,
1-
1&
#4540
0!
0.
#4550
1!
1.
b100010 3
0&
#4560
0#
0!
0.
00
#4570
1!
1.
#4580
0!
0.
#4590
1!
1.
#4600
1#
0!
0.
10
#4610
1!
1.
b100001 3
0-
1&
#4620
0!
0.
#4630
1!
1.
b100000 3
0&
#4640
1"
0#
0!
0.
00
1/
#4650
1!
1.
b100001 3
1&
#4660
0!
0.
#4670
1!
1.
b100010 3
1-
0&
#4680
1#
0!
0.
10
#4690
1!
1.
b100011 3
1&
#4700
0!
0.
#4710
1!
1.
b100100 3
1,
0-
0&
#4720
0#
0!
0.
00
#4730
1!
1.
b100101 3
1&
#4740
0!
0.
#4750
1!
1.
b100110 3
1-
0&
#4760
1#
0!
0.
10
#4770
1!
1.
b100111 3
1&
#4780
0!
0.
#4790
1!
1.
b101000 3
1+
0,
0-
0&
#4800
0"
0#
0!
0.
00
0/
#4810
1!
1.
#4820
0!
0.
#4830
1!
1.
#4840
1#
0!
0.
10
#4850
1!
1.
b100111 3
0+
1,
1-
1&
#4860
0!
0.
#4870
1!
1.
b100110 3
0&
#4880
0#
0!
0.
00
#4890
1!
1.
#4900
0!
0.
#4910
1!
1.
#4920
1#
0!
0.
10
#4930
1!
1.
b100101 3
0-
1&
#4940
0!
0.
#4950
1!
1.
b100100 3
0&
#4960
1"
0#
0!
0.
00
1/
#4970
1!
1.
b100101 3
1&
#4980
0!
0.
#4990
1!
1.
b100110 3
1-
0&
